{"nodes": [{"id": "bookscreen_bookscreen", "label": "BookScreen", "file_type": "code", "source_file": "src/screens/main/BookScreen.jsx", "source_location": null, "source_url": null, "captured_at": null, "author": null, "contributor": null}], "edges": [{"source": "bookscreen_bookscreen", "target": "colors_colors", "relation": "references", "confidence": "EXTRACTED", "confidence_score": 1.0, "source_file": "src/screens/main/BookScreen.jsx", "source_location": null, "weight": 1.0}, {"source": "bookscreen_bookscreen", "target": "fonts_fonts", "relation": "references", "confidence": "EXTRACTED", "confidence_score": 1.0, "source_file": "src/screens/main/BookScreen.jsx", "source_location": null, "weight": 1.0}], "hyperedges": []}